odoo/addons/purchase_work_acceptance_late_fines/README.rst
odoo/addons/purchase_work_acceptance_late_fines/__init__.py
odoo/addons/purchase_work_acceptance_late_fines/__manifest__.py
odoo/addons/purchase_work_acceptance_late_fines/i18n/es.po
odoo/addons/purchase_work_acceptance_late_fines/i18n/purchase_work_acceptance_late_fines.pot
odoo/addons/purchase_work_acceptance_late_fines/models/__init__.py
odoo/addons/purchase_work_acceptance_late_fines/models/account_move.py
odoo/addons/purchase_work_acceptance_late_fines/models/res_company.py
odoo/addons/purchase_work_acceptance_late_fines/models/res_config_settings.py
odoo/addons/purchase_work_acceptance_late_fines/models/work_acceptance.py
odoo/addons/purchase_work_acceptance_late_fines/readme/CONFIGURE.rst
odoo/addons/purchase_work_acceptance_late_fines/readme/CONTRIBUTORS.rst
odoo/addons/purchase_work_acceptance_late_fines/readme/DESCRIPTION.rst
odoo/addons/purchase_work_acceptance_late_fines/readme/USAGE.rst
odoo/addons/purchase_work_acceptance_late_fines/security/ir.model.access.csv
odoo/addons/purchase_work_acceptance_late_fines/security/security.xml
odoo/addons/purchase_work_acceptance_late_fines/static/description/icon.png
odoo/addons/purchase_work_acceptance_late_fines/static/description/index.html
odoo/addons/purchase_work_acceptance_late_fines/tests/__init__.py
odoo/addons/purchase_work_acceptance_late_fines/tests/test_work_acceptance_late_fine.py
odoo/addons/purchase_work_acceptance_late_fines/views/account_move_views.xml
odoo/addons/purchase_work_acceptance_late_fines/views/res_config_settings_views.xml
odoo/addons/purchase_work_acceptance_late_fines/views/work_acceptance_views.xml
odoo/addons/purchase_work_acceptance_late_fines/wizards/__init__.py
odoo/addons/purchase_work_acceptance_late_fines/wizards/work_acceptance_create_fines.py
odoo/addons/purchase_work_acceptance_late_fines/wizards/work_acceptance_create_fines_views.xml
odoo_addon_purchase_work_acceptance_late_fines-15.0.1.1.0.3.dist-info/METADATA
odoo_addon_purchase_work_acceptance_late_fines-15.0.1.1.0.3.dist-info/WHEEL
odoo_addon_purchase_work_acceptance_late_fines-15.0.1.1.0.3.dist-info/top_level.txt
odoo_addon_purchase_work_acceptance_late_fines-15.0.1.1.0.3.dist-info/RECORD
